odoo8_addon_medical_prescription_state-8.0.1.1.0.99.dev4-py2.7-nspkg.pth
odoo_addons/medical_prescription_state/__openerp__.py
odoo_addons/medical_prescription_state/__init__.py
odoo_addons/medical_prescription_state/README.rst
odoo_addons/medical_prescription_state/security/ir.model.access.csv
odoo_addons/medical_prescription_state/models/medical_prescription_order.py
odoo_addons/medical_prescription_state/models/medical_prescription_order_state.py
odoo_addons/medical_prescription_state/models/__init__.py
odoo_addons/medical_prescription_state/i18n/pt_BR.po
odoo_addons/medical_prescription_state/views/prescription_order_view.xml
odoo_addons/medical_prescription_state/views/medical_menu.xml
odoo_addons/medical_prescription_state/views/medical_prescription_order_state_view.xml
odoo8_addon_medical_prescription_state-8.0.1.1.0.99.dev4.dist-info/top_level.txt
odoo8_addon_medical_prescription_state-8.0.1.1.0.99.dev4.dist-info/WHEEL
odoo8_addon_medical_prescription_state-8.0.1.1.0.99.dev4.dist-info/RECORD
odoo8_addon_medical_prescription_state-8.0.1.1.0.99.dev4.dist-info/metadata.json
odoo8_addon_medical_prescription_state-8.0.1.1.0.99.dev4.dist-info/DESCRIPTION.rst
odoo8_addon_medical_prescription_state-8.0.1.1.0.99.dev4.dist-info/METADATA
odoo8_addon_medical_prescription_state-8.0.1.1.0.99.dev4.dist-info/namespace_packages.txt
